cohdl/__init__.py
cohdl/_compiler/__init__.py
cohdl/_compiler/backend/__init__.py
cohdl/_compiler/backend/vhdl/__init__.py
cohdl/_compiler/backend/vhdl/_vhdl_assembler.py
cohdl/_compiler/backend/vhdl/_vhdl_repr.py
cohdl/_compiler/backend/vhdl/backend.py
cohdl/_compiler/frontend/__init__.py
cohdl/_compiler/frontend/_frontend.py
cohdl/_compiler/frontend/_generate_ir.py
cohdl/_compiler/frontend/_prepare_ast.py
cohdl/_compiler/frontend/_prepare_ast_out.py
cohdl/_compiler/frontend/_traceback.py
cohdl/_compiler/frontend/_value_branch.py
cohdl/_core/__init__.py
cohdl/_core/_array.py
cohdl/_core/_array.pyi
cohdl/_core/_bit.py
cohdl/_core/_bit.pyi
cohdl/_core/_bit_vector.py
cohdl/_core/_bit_vector.pyi
cohdl/_core/_boolean.py
cohdl/_core/_boolean.pyi
cohdl/_core/_collect_ast_and_scope.py
cohdl/_core/_context.py
cohdl/_core/_context.pyi
cohdl/_core/_enum.py
cohdl/_core/_inline.py
cohdl/_core/_integer.py
cohdl/_core/_integer.pyi
cohdl/_core/_intrinsic.py
cohdl/_core/_intrinsic.pyi
cohdl/_core/_intrinsic_definitions.py
cohdl/_core/_intrinsic_definitions.pyi
cohdl/_core/_intrinsic_operations.py
cohdl/_core/_intrinsic_operations.pyi
cohdl/_core/_op.py
cohdl/_core/_primitive_type.py
cohdl/_core/_signed.py
cohdl/_core/_signed.pyi
cohdl/_core/_type_qualifier.py
cohdl/_core/_type_qualifier.pyi
cohdl/_core/_unsigned.py
cohdl/_core/_unsigned.pyi
cohdl/_core/_ir/__init__.py
cohdl/_core/_ir/_repr.py
cohdl/std/__init__.py
cohdl/std/_assignable_type.py
cohdl/std/_assignable_type.pyi
cohdl/std/_compile.py
cohdl/std/_context.py
cohdl/std/_context.pyi
cohdl/std/_core_utility.py
cohdl/std/_core_utility.pyi
cohdl/std/_crc.py
cohdl/std/_exception.py
cohdl/std/_exception.pyi
cohdl/std/_fixed.py
cohdl/std/_fixed.pyi
cohdl/std/_formal.py
cohdl/std/_prefix.py
cohdl/std/_prefix.pyi
cohdl/std/_record.py
cohdl/std/_record.pyi
cohdl/std/_template.py
cohdl/std/_template.pyi
cohdl/std/bitfield.py
cohdl/std/bitfield.pyi
cohdl/std/enum.py
cohdl/std/enum.pyi
cohdl/std/spi.py
cohdl/std/spi.pyi
cohdl-0.2.4.dist-info/licenses/LICENSE
cohdl-0.2.4.dist-info/METADATA
cohdl-0.2.4.dist-info/WHEEL
cohdl-0.2.4.dist-info/top_level.txt
cohdl-0.2.4.dist-info/RECORD
