Metadata-Version: 2.4
Name: cohdl
Version: 0.2.4
Summary: A Python to VHDL compiler
Author-email: Alexander Forster <alexander.forster123@gmail.com>
Project-URL: Homepage, https://github.com/alexander-forster/cohdl
Classifier: Programming Language :: Python :: 3
Classifier: License :: OSI Approved :: MIT License
Requires-Python: >=3.11
License-File: LICENSE
Dynamic: license-file
